pyhadoopapi/__init__.py
pyhadoopapi/__main__.py
pyhadoopapi/client.py
pyhadoopapi/cluster.py
pyhadoopapi/cluster_command.py
pyhadoopapi/hdfs_command.py
pyhadoopapi/oozie.py
pyhadoopapi/oozie_command.py
pyhadoopapi/submit_command.py
pyhadoopapi/webhdfs.py
pyhadoopapi/apps/monitor/__main__.py
pyhadoopapi/apps/monitor/api.py
pyhadoopapi/apps/monitor/app.py
pyhadoopapi/apps/monitor/views.py
pyhadoopapi/apps/monitor/assets/css/c3.min.css
pyhadoopapi/apps/monitor/assets/css/main.css
pyhadoopapi/apps/monitor/assets/js/c3.min.js
pyhadoopapi/apps/monitor/assets/js/d3.min.js
pyhadoopapi/apps/monitor/assets/js/queues.js
pyhadoopapi/apps/monitor/templates/base.html
pyhadoopapi/apps/monitor/templates/cluster.html
pyhadoopapi/apps/tracker/__init__.py
pyhadoopapi/apps/tracker/__main__.py
pyhadoopapi/apps/tracker/api.py
pyhadoopapi/apps/tracker/service.py
pyhadoopapi/apps/tracker/tasks.py
pyhadoopapi/apps/tracker/views.py
pyhadoopapi/apps/tracker/assets/css/c3.min.css
pyhadoopapi/apps/tracker/assets/css/main.css
pyhadoopapi/apps/tracker/assets/js/c3.min.js
pyhadoopapi/apps/tracker/assets/js/d3.min.js
pyhadoopapi/apps/tracker/assets/js/queues.js
pyhadoopapi/apps/tracker/assets/js/tracking.js
pyhadoopapi/apps/tracker/templates/base.html
pyhadoopapi/apps/tracker/templates/cluster.html
pyhadoopapi-0.9.3.dist-info/METADATA
pyhadoopapi-0.9.3.dist-info/RECORD
pyhadoopapi-0.9.3.dist-info/WHEEL
pyhadoopapi-0.9.3.dist-info/top_level.txt
