Metadata-Version: 2.1
Name: pyhadoopapi
Version: 0.9.3
Summary: A client library for Apache Knox
Home-page: https://github.com/alexmilowski/python-hadoop-rest-api
Author: Alex Miłowski
Author-email: alex@milowski.com
License: Apache 2.0
Platform: UNKNOWN
Classifier: Development Status :: 4 - Beta
Classifier: Intended Audience :: Developers
Classifier: Topic :: Software Development :: Libraries
Classifier: License :: OSI Approved :: Apache Software License
Classifier: Programming Language :: Python :: 3
Classifier: Programming Language :: Python :: 3.3
Classifier: Programming Language :: Python :: 3.4
Classifier: Programming Language :: Python :: 3.5
Requires-Dist: requests
Requires-Dist: flask
Requires-Dist: redis
Requires-Dist: cryptography
